{
    "data": [
        {
            "id": "2",
            "type": "percentages",
            "attributes": {
                "companyName": "Target",
                "percentage": "3%",
                "category": "Electronics",
                "card": "Chase"
            },
            "links": {
                "self": "http://localhost:9090/cashBackFinder/api/percentages/2"
            }
        },
        {
            "id": "1",
            "type": "percentages",
            "attributes": {
                "companyName": "Walmart",
                "percentage": "3%",
                "category": "food",
                "card": "Bank of America"
            },
            "links": {
                "self": "http://localhost:9090/cashBackFinder/api/percentages/1"
            }
        },
        {
            "id": "6",
            "type": "percentages",
            "attributes": {
                "companyName": "Costco",
                "percentage": "5%",
                "category": "Retail",
                "card": "Discover"
            },
            "links": {
                "self": "http://localhost:9090/cashBackFinder/api/percentages/6"
            }
        },
        {
            "id": "5",
            "type": "percentages",
            "attributes": {
                "companyName": "Sam's Club",
                "percentage": "3%",
                "category": "Retail",
                "card": "Chase"
            },
            "links": {
                "self": "http://localhost:9090/cashBackFinder/api/percentages/5"
            }
        },
        {
            "id": "4",
            "type": "percentages",
            "attributes": {
                "companyName": "Shell",
                "percentage": "5%",
                "category": "Gas",
                "card": "Citi Bank"
            },
            "links": {
                "self": "http://localhost:9090/cashBackFinder/api/percentages/4"
            }
        },
        {
            "id": "3",
            "type": "percentages",
            "attributes": {
                "companyName": "Kroger",
                "percentage": "1%",
                "category": "Retail",
                "card": "Discover"
            },
            "links": {
                "self": "http://localhost:9090/cashBackFinder/api/percentages/3"
            }
        }
    ],
    "meta": {
        "totalResourceCount": null
    }
}